xglove/__init__.py
xglove/glove.py
xglove/connectors/__init__.py
xglove/connectors/client/__init__.py
xglove/connectors/client/client.py
xglove/connectors/host/__init__.py
xglove/connectors/host/host.py
xglove/data/__init__.py
xglove/data/calib_raw.json
xglove/drivers/__init__.py
xglove/drivers/accelerometer.py
xglove/drivers/fingers.py
xglove/drivers/interface.py
xglove/utils/__init__.py
xglove/utils/calib_updating.py
xglove/utils/code_updating.py
xglove-0.3.2.dist-info/licenses/LICENSE
xglove-0.3.2.dist-info/METADATA
xglove-0.3.2.dist-info/WHEEL
xglove-0.3.2.dist-info/top_level.txt
xglove-0.3.2.dist-info/RECORD
