Metadata-Version: 2.4
Name: xglove
Version: 0.3.2
Summary: Библиотека созданная для устройства XGlove
Requires-Python: >=3.8
License-File: LICENSE
Requires-Dist: paramiko==3.5.1
Requires-Dist: numpy==1.24.4
Requires-Dist: pillow==10.4.0
Requires-Dist: pyserial==3.5
Requires-Dist: adafruit-circuitpython-ads1x15==2.4.4; platform_machine == "armv7l" or platform_machine == "aarch64"
Requires-Dist: luma.oled==3.14.0; platform_machine == "armv7l" or platform_machine == "aarch64"
Requires-Dist: smbus2==0.5.0; platform_machine == "armv7l" or platform_machine == "aarch64"
Requires-Dist: Adafruit-Blinka==8.62.0; platform_machine == "armv7l" or platform_machine == "aarch64"
Requires-Dist: RPi.GPIO==0.7.1; platform_machine == "armv7l" or platform_machine == "aarch64"
Dynamic: description
Dynamic: description-content-type
Dynamic: license-file
Dynamic: requires-dist
Dynamic: requires-python
Dynamic: summary
